LICENSE
MANIFEST.in
README
requirements.txt
setup.py
gicowa/__init__.py
gicowa/gicowa.py
gicowa.egg-info/PKG-INFO
gicowa.egg-info/SOURCES.txt
gicowa.egg-info/dependency_links.txt
gicowa.egg-info/entry_points.txt
gicowa.egg-info/requires.txt
gicowa.egg-info/top_level.txt
gicowa/impl/__init__.py
gicowa/impl/mail.py
gicowa/impl/output.py
gicowa/impl/persistence.py
gicowa/impl/timestamp.py
test/test_gicowa.py