Metadata-Version: 1.1
Name: gicowa
Version: 1.2.2
Summary: GitHub Commit Watcher
Home-page: https://github.com/AurelienLourot/github-commit-watcher
Author: Aurelien Lourot
Author-email: aurelien.lourot@gmail.com
License: public domain
Download-URL: https://github.com/AurelienLourot/github-commit-watcher/tarball/1.2.2
Keywords: gicowa,github,commit,commits,watcher,watch,push,pushed,notification,notifications
Platform: UNKNOWN
Classifier: Development Status :: 4 - Beta
Classifier: Environment :: Console
Classifier: Intended Audience :: Developers
Classifier: License :: Public Domain
Classifier: Natural Language :: English
Classifier: Operating System :: POSIX :: Linux
Classifier: Programming Language :: Python :: 2.7
Classifier: Topic :: Software Development :: Version Control
Classifier: Topic :: Utilities
